pyec
