Metadata-Version: 1.0
Name: PyEC
Version: 0.2.5
Summary: Evolutionary computation package
Home-page: http://www.alockett.com/pyec/docs/0.2/index.html
Author: Alan J Lockett
Author-email: UNKNOWN
License: UNKNOWN
Platform: UNKNOWN
